{
    "marketingData": [
        {
            "callId": "US00112",
            "Date": "08/06/2018",
            "vendorName": "WIP ALEX Ram", 
            "vendorContact": "79825623",
            "vendorPhoneNumber": "546465554", 
            "client": "Weehxmt", 
            "status": "Submit"
        },
        {
            "callId": "US00112",
            "Date": "07/06/2017",
            "vendorName": "WIP ALEX Ram", 
            "vendorContact": "79825623",
            "vendorPhoneNumber": "546465554", 
            "client": "Weehxmt", 
            "status": "Submit"
        },
        {
            "callId": "US00112",
            "Date": "09/06/2017",
            "vendorName": "WIP ALEX Ram", 
            "vendorContact": "79825623",
            "vendorPhoneNumber": "546465554", 
            "client": "Weehxmt", 
            "status": "Submit"
        },
        {
            "callId": "US00112",
            "Date": "08/10/2018",
            "vendorName": "WIP ALEX Ram", 
            "vendorContact": "79825623",
            "vendorPhoneNumber": "546465554", 
            "client": "Weehxmt", 
            "status": "Submit"
        },
        {
            "callId": "US00112",
            "Date": "08/05/2018",
            "vendorName": "WIP ALEX Ram", 
            "vendorContact": "79825623",
            "vendorPhoneNumber": "546465554", 
            "client": "Weehxmt", 
            "status": "Submit"
        },
        {
            "callId": "US00112",
            "Date": "17/07/2018",
            "vendorName": "WIP ALEX Ram", 
            "vendorContact": "79825623",
            "vendorPhoneNumber": "546465554", 
            "client": "Weehxmt", 
            "status": "Submit"
        },
        {
            "callId": "US00112",
            "Date": "07/08/2014",
            "vendorName": "WIP ALEX Ram", 
            "vendorContact": "79825623",
            "vendorPhoneNumber": "546465554", 
            "client": "Weehxmt", 
            "status": "Submit"
        },
        {
            "callId": "US00221",
            "Date": "05.07.18",
            "vendorName": "WIP ALEX Ram", 
            "vendorContact": "79825623",
            "vendorPhoneNumber": "546465554", 
            "client": "Weehxmt", 
            "status": "Submit"
        },
        {
            "callId": "US00112",
            "Date": "08.06.18",
            "vendorName": "WIP ALEX Ram", 
            "vendorContact": "79825623",
            "vendorPhoneNumber": "546465554", 
            "client": "Weehxmt", 
            "status": "Submit"
        },
        {
            "callId": "US00112",
            "Date": "08.06.18",
            "vendorName": "WIP ALEX Ram", 
            "vendorContact": "79825623",
            "vendorPhoneNumber": "546465554", 
            "client": "Weehxmt", 
            "status": "Submit"
        },
        {
            "callId": "US00112",
            "Date": "08.06.18",
            "vendorName": "WIP ALEX Ram", 
            "vendorContact": "79825623",
            "vendorPhoneNumber": "546465554", 
            "client": "Weehxmt", 
            "status": "Submit"
        },
        {
            "callId": "US00112",
            "Date": "08.06.18",
            "vendorName": "WIP ALEX Ram", 
            "vendorContact": "79825623",
            "vendorPhoneNumber": "546465554", 
            "client": "Weehxmt", 
            "status": "Submit"
        },
        {
            "callId": "US00112",
            "Date": "08.06.18",
            "vendorName": "WIP ALEX Ram", 
            "vendorContact": "79825623",
            "vendorPhoneNumber": "546465554", 
            "client": "Weehxmt", 
            "status": "Submit"
        },
        {
            "callId": "US00112",
            "Date": "08.06.18",
            "vendorName": "WIP ALEX Ram", 
            "vendorContact": "79825623",
            "vendorPhoneNumber": "546465554", 
            "client": "Weehxmt", 
            "status": "Submit"
        },
        {
            "callId": "US00112",
            "Date": "08.06.18",
            "vendorName": "WIP ALEX Ram", 
            "vendorContact": "79825623",
            "vendorPhoneNumber": "546465554", 
            "client": "Weehxmt", 
            "status": "Submit"
        }


    ]
}